nieto_curcio_example/__init__.py
nieto_curcio_example/main.py
nieto_curcio_example/some_module.py
nieto_curcio_example-0.2.0.dist-info/METADATA
nieto_curcio_example-0.2.0.dist-info/WHEEL
nieto_curcio_example-0.2.0.dist-info/entry_points.txt
nieto_curcio_example-0.2.0.dist-info/RECORD
