Metadata-Version: 2.4
Name: nieto-curcio-example
Version: 0.2.0
Summary: Add your description here
Author-email: dsm-ll <diogo@liquidloans.io>
Requires-Python: >=3.9
Requires-Dist: requests>=2.32.3
